{"_type":"export","__export_format":4,"__export_date":"2022-08-23T20:01:40.861Z","__export_source":"insomnia.desktop.app:v2022.5.1","resources":[{"_id":"req_d4a9277002d94de1b38c44b59ad6414b","parentId":"wrk_f1c42dfc073f4480b248e66fdb26ef18","modified":1661284846900,"created":1661274899358,"url":"{{base_url}}/","name":"Buscar scraping","description":"","method":"GET","body":{},"parameters":[],"headers":[],"authentication":{},"metaSortKey":-1661274899358,"isPrivate":false,"settingStoreCookies":true,"settingSendCookies":true,"settingDisableRenderRequestBody":false,"settingEncodeUrl":true,"settingRebuildPath":true,"settingFollowRedirects":"global","_type":"request"},{"_id":"wrk_f1c42dfc073f4480b248e66fdb26ef18","parentId":null,"modified":1661274899342,"created":1661274899342,"name":"New Document","description":"","scope":"design","_type":"workspace"},{"_id":"env_b129f595090abcb1bd04ba1d2c592887bf6f3370","parentId":"wrk_f1c42dfc073f4480b248e66fdb26ef18","modified":1661274962977,"created":1661274899353,"name":"Base Environment","data":{},"dataPropertyOrder":{},"color":null,"isPrivate":false,"metaSortKey":1661274899353,"_type":"environment"},{"_id":"jar_b129f595090abcb1bd04ba1d2c592887bf6f3370","parentId":"wrk_f1c42dfc073f4480b248e66fdb26ef18","modified":1661274899356,"created":1661274899356,"name":"Default Jar","cookies":[],"_type":"cookie_jar"},{"_id":"spc_e32150332c07404486b7b8e8a04fb242","parentId":"wrk_f1c42dfc073f4480b248e66fdb26ef18","modified":1661284882453,"created":1661274899351,"fileName":"Scraping info simples","contents":"","contentType":"yaml","_type":"api_spec"},{"_id":"uts_b61e621f46204904b93660564261beca","parentId":"wrk_f1c42dfc073f4480b248e66fdb26ef18","modified":1661274899358,"created":1661274899358,"name":"Example Test Suite","_type":"unit_test_suite"},{"_id":"env_3e9ebb81369b45b9b17779006d943db1","parentId":"env_b129f595090abcb1bd04ba1d2c592887bf6f3370","modified":1661274985961,"created":1661274966434,"name":"scraping","data":{"base_url":"http://localhost:4444"},"dataPropertyOrder":{"&":["base_url"]},"color":null,"isPrivate":false,"metaSortKey":1661274966434,"_type":"environment"}]}